skbot/__init__.py
skbot/_numba_overloads.py
skbot/ignition/__init__.py
skbot/ignition/fuel.py
skbot/ignition/messages.py
skbot/ignition/subscriber.py
skbot/ignition/transformations.py
skbot/ignition/sdformat/__init__.py
skbot/ignition/sdformat/create_frame_graph.py
skbot/ignition/sdformat/exceptions.py
skbot/ignition/sdformat/load_as_generic.py
skbot/ignition/sdformat/sdformat.py
skbot/ignition/sdformat/transform_factory.py
skbot/ignition/sdformat/bindings/__init__.py
skbot/ignition/sdformat/bindings/v10/__init__.py
skbot/ignition/sdformat/bindings/v10/actor.py
skbot/ignition/sdformat/bindings/v10/collision.py
skbot/ignition/sdformat/bindings/v10/geometry.py
skbot/ignition/sdformat/bindings/v10/joint.py
skbot/ignition/sdformat/bindings/v10/light.py
skbot/ignition/sdformat/bindings/v10/link.py
skbot/ignition/sdformat/bindings/v10/model.py
skbot/ignition/sdformat/bindings/v10/physics.py
skbot/ignition/sdformat/bindings/v10/scene.py
skbot/ignition/sdformat/bindings/v10/sensor.py
skbot/ignition/sdformat/bindings/v10/state.py
skbot/ignition/sdformat/bindings/v10/visual.py
skbot/ignition/sdformat/bindings/v10/world.py
skbot/ignition/sdformat/bindings/v12/__init__.py
skbot/ignition/sdformat/bindings/v12/actor.py
skbot/ignition/sdformat/bindings/v12/collision.py
skbot/ignition/sdformat/bindings/v12/geometry.py
skbot/ignition/sdformat/bindings/v12/joint.py
skbot/ignition/sdformat/bindings/v12/light.py
skbot/ignition/sdformat/bindings/v12/link.py
skbot/ignition/sdformat/bindings/v12/model.py
skbot/ignition/sdformat/bindings/v12/physics.py
skbot/ignition/sdformat/bindings/v12/scene.py
skbot/ignition/sdformat/bindings/v12/sensor.py
skbot/ignition/sdformat/bindings/v12/state.py
skbot/ignition/sdformat/bindings/v12/visual.py
skbot/ignition/sdformat/bindings/v12/world.py
skbot/ignition/sdformat/bindings/v13/__init__.py
skbot/ignition/sdformat/bindings/v13/actor.py
skbot/ignition/sdformat/bindings/v13/collision.py
skbot/ignition/sdformat/bindings/v13/geometry.py
scikit_bot-0.14.0.dist-info/LICENSE
scikit_bot-0.14.0.dist-info/METADATA
scikit_bot-0.14.0.dist-info/WHEEL
scikit_bot-0.14.0.dist-info/top_level.txt
scikit_bot-0.14.0.dist-info/RECORD
