Metadata-Version: 2.1
Name: scikit-bot
Version: 0.14.0
Summary: Robotics in Python
License: UNKNOWN
Platform: UNKNOWN
Classifier: Programming Language :: Python :: 3
Classifier: License :: OSI Approved :: Apache Software License
Classifier: Framework :: Robot Framework :: Library
License-File: LICENSE
Requires-Dist: numpy (==1.21.5)
Requires-Dist: scipy (==1.7.3)
Requires-Dist: numba (==0.55.1)
Provides-Extra: build
Requires-Dist: build (==0.7.0) ; extra == 'build'
Requires-Dist: twine (==3.8.0) ; extra == 'build'
Provides-Extra: dev
Requires-Dist: lxml-stubs (==0.3.1) ; extra == 'dev'
Requires-Dist: python-semantic-release (==7.25.2) ; extra == 'dev'
Provides-Extra: docs
Requires-Dist: sphinx (==4.4.0) ; extra == 'docs'
Requires-Dist: numpydoc (==1.2) ; extra == 'docs'
Requires-Dist: sphinx-autodoc-typehints (==1.17.0) ; extra == 'docs'
Requires-Dist: matplotlib (==3.5.1) ; extra == 'docs'
Requires-Dist: pydata-sphinx-theme (==0.8.0) ; extra == 'docs'
Requires-Dist: cachetools (==5.0.0) ; extra == 'docs'
Requires-Dist: sphinx-gallery (==0.10.1) ; extra == 'docs'
Requires-Dist: xsdata (==22.1) ; extra == 'docs'
Requires-Dist: lxml (==4.6.5) ; extra == 'docs'
Provides-Extra: ignition
Requires-Dist: pyzmq (==22.3.0) ; extra == 'ignition'
Requires-Dist: betterproto (==1.2.5) ; extra == 'ignition'
Requires-Dist: psutil (==5.9.0) ; extra == 'ignition'
Requires-Dist: requests (==2.27.1) ; extra == 'ignition'
Requires-Dist: xsdata (==22.1) ; extra == 'ignition'
Requires-Dist: lxml (==4.6.5) ; extra == 'ignition'
Requires-Dist: cachetools (==5.0.0) ; extra == 'ignition'
Provides-Extra: linting
Requires-Dist: flake8 (==4.0.1) ; extra == 'linting'
Requires-Dist: black (==21.12b0) ; extra == 'linting'
Provides-Extra: testing
Requires-Dist: pytest (==7.0.1) ; extra == 'testing'
Requires-Dist: coverage[toml] (==6.3.2) ; extra == 'testing'
